apertium/__init__.py
apertium/installer.py
apertium/iso639.py
apertium/mode_search.py
apertium/py.typed
apertium/utils.py
apertium/analysis/__init__.py
apertium/generation/__init__.py
apertium/tagger/__init__.py
apertium/translation/__init__.py
apertium-0.2.4.dist-info/LICENSE
apertium-0.2.4.dist-info/METADATA
apertium-0.2.4.dist-info/WHEEL
apertium-0.2.4.dist-info/top_level.txt
apertium-0.2.4.dist-info/RECORD
