Metadata-Version: 2.1
Name: apertium
Version: 0.2.4
Summary: Apertium core modules available in Python
Home-page: https://github.com/apertium/apertium-python
Author: Lokendra Singh, Arghya Bhatttacharya, Sushain K. Cherivirala, Andi Qu
Author-email: sushain@skc.name
License: GNU General Public License v3.0
Keywords: apertium machine translation linguistics
Platform: Debian
Platform: Windows
Classifier: Development Status :: 3 - Alpha
Classifier: Topic :: Text Processing :: Linguistic
Classifier: License :: OSI Approved :: GNU General Public License v3 or later (GPLv3+)
Classifier: Intended Audience :: Science/Research
Classifier: Intended Audience :: Developers
Classifier: Programming Language :: Python :: 3.6
Classifier: Programming Language :: Python :: 3.7
Classifier: Programming Language :: Python :: 3.8
Classifier: Programming Language :: Python :: 3 :: Only
Classifier: Operating System :: Microsoft :: Windows
Classifier: Operating System :: POSIX
Requires-Python: >=3.5
License-File: LICENSE
Requires-Dist: apertium-streamparser ==5.0.2
